gacrawler/Berita.py
gacrawler/Genetic.py
gacrawler/Symbiotic.py
gacrawler/Tfidf.py
gacrawler/__init__.py
gacrawler/__main__.py
gacrawler/bfs.py
gacrawler/config.py
gacrawler/connection.py
gacrawler/const.py
gacrawler/function.py
gacrawler/gacrawler.py
gacrawler/gsearch.py
gacrawler/init_command.py
gacrawler_alfonsusw-3.2.2.dist-info/LICENSE
gacrawler_alfonsusw-3.2.2.dist-info/METADATA
gacrawler_alfonsusw-3.2.2.dist-info/WHEEL
gacrawler_alfonsusw-3.2.2.dist-info/entry_points.txt
gacrawler_alfonsusw-3.2.2.dist-info/top_level.txt
gacrawler_alfonsusw-3.2.2.dist-info/RECORD
