Metadata-Version: 2.1
Name: gacrawler-alfonsusw
Version: 3.2.2
Summary: A fully functioned Focused Web Crawler using Genetic Algorithm
Home-page: UNKNOWN
Author: Alfonsus Wilson
Author-email: alfonsus.wilson@gmail.com
License: UNKNOWN
Platform: UNKNOWN
Classifier: Programming Language :: Python :: 2 :: Only
Classifier: License :: OSI Approved :: MIT License
Classifier: Operating System :: OS Independent
Requires-Dist: markdown
Requires-Dist: scikit-learn
Requires-Dist: google-api-python-client
Requires-Dist: pprint
Requires-Dist: beautifulsoup4
Requires-Dist: requests
Requires-Dist: pysastrawi
Requires-Dist: furl
Requires-Dist: gensim
Requires-Dist: pathos
